LICENSE
README.md
setup.py
capsolver_api/__init__.py
capsolver_api/capsolver_api.py
capsolver_api/exceptions.py
capsolver_api.egg-info/PKG-INFO
capsolver_api.egg-info/SOURCES.txt
capsolver_api.egg-info/dependency_links.txt
capsolver_api.egg-info/requires.txt
capsolver_api.egg-info/top_level.txt
capsolver_api/recognitions/aws_waf.py
capsolver_api/recognitions/funcaptcha.py
capsolver_api/recognitions/hcaptcha.py
capsolver_api/recognitions/image_to_task.py
capsolver_api/recognitions/recaptcha.py
capsolver_api/tasks/cloudflare_challenge.py
capsolver_api/tasks/cloudflare_turnstile.py
capsolver_api/tasks/datadome.py
capsolver_api/tasks/funcaptcha.py
capsolver_api/tasks/geetest.py
capsolver_api/tasks/hcaptcha.py
capsolver_api/tasks/mtcaptcha.py
capsolver_api/tasks/recaptchav2.py
capsolver_api/tasks/recaptchav3.py