Metadata-Version: 2.1
Name: capsolver-api
Version: 1.0.7
Summary: capsolver.com library for Python
Home-page: https://github.com/seadhy/capsolver-api
Author: seadhy
Author-email: contact@seadhy.com
License: MIT
Project-URL: Documentation, https://github.com/seadhy/capsolver-api#capsolver-api-for-python
Project-URL: Source, https://github.com/seadhy/capsolver-api/tree/main/capsolver_api
Project-URL: Bug Tracker, https://github.com/seadhy/capsolver-api/issues
Classifier: Programming Language :: Python :: 3
Classifier: License :: OSI Approved :: MIT License
Classifier: Operating System :: OS Independent
Requires-Python: >=3
License-File: LICENSE
